cuda_optics/__init__.py
cuda_optics/bin/engine_cpp.dll
cuda_optics/bin/engine_cpp.so
cuda_optics/bin/engine_cuda.dll
cuda_optics/bin/engine_cuda.so
cuda_optics-0.1.4.dist-info/licenses/LICENSE
examples/cuda_optics_documentation.ipynb
examples/cuda_optics_original.py
src_native/engine_cpp.cpp
src_native/engine_cuda.cu
cuda_optics-0.1.4.dist-info/METADATA
cuda_optics-0.1.4.dist-info/WHEEL
cuda_optics-0.1.4.dist-info/top_level.txt
cuda_optics-0.1.4.dist-info/RECORD
