Metadata-Version: 2.4
Name: cuda_optics
Version: 0.1.4
Summary: A high-performance optical ray tracer with C++ and CUDA backends.
Author-email: Adityavardhan Srivastava <sadityavardhan1@gmail.com>
License: MIT
Requires-Python: >=3.8
License-File: LICENSE
Requires-Dist: numpy
Requires-Dist: matplotlib
Requires-Dist: scipy
Dynamic: license-file
